djdynatable/__init__.py
djdynatable/admin.py
djdynatable/apps.py
djdynatable/compat.py
djdynatable/core.py
djdynatable/exception.py
djdynatable/handler.py
djdynatable/models.py
djdynatable/response.py
djdynatable/serializer.py
djdynatable/tests.py
djdynatable/urls.py
djdynatable/utils.py
djdynatable/views.py
djdynatable/migrations/0001_initial.py
djdynatable/migrations/__init__.py
djdynatable-1.0.4.dist-info/METADATA
djdynatable-1.0.4.dist-info/WHEEL
djdynatable-1.0.4.dist-info/top_level.txt
djdynatable-1.0.4.dist-info/RECORD
