Metadata-Version: 2.1
Name: djdynatable
Version: 1.0.4
Author: Anand Raj
Author-email: anand98.ar@gmail.com
License: UNKNOWN
Classifier: Development Status :: 5 - Production/Stable
Classifier: Intended Audience :: Education
Classifier: Operating System :: Microsoft :: Windows :: Windows 10
Classifier: Programming Language :: Python :: 3
Requires-Python: >=3.8
Requires-Dist: django
Requires-Dist: djangorestframework
